device_manager/__init__.py
device_manager/device.py
device_manager/manager.py
device_manager/scanner/__init__.py
device_manager/scanner/_base.py
device_manager/scanner/_linux.py
device_manager/scanner/_win32.py
device_manager/scanner/nmap.py
device_manager/utils/__init__.py
device_manager/utils/usb_vendor_database.py
device_manager-0.2.4.dist-info/AUTHORS
device_manager-0.2.4.dist-info/LICENSE
device_manager-0.2.4.dist-info/METADATA
device_manager-0.2.4.dist-info/WHEEL
device_manager-0.2.4.dist-info/top_level.txt
device_manager-0.2.4.dist-info/RECORD
