Metadata-Version: 2.1
Name: device-manager
Version: 0.2.4
Summary: A tool for searching and managing plug-and-play devices
Home-page: https://github.com/zea2/DeviceManager
Author: Forschungszentrum Jülich GmbH - ZEA-2
License: UNKNOWN
Download-URL: https://github.com/zea2/DeviceManager/archive/v0.2.4.zip
Platform: UNKNOWN
Classifier: Programming Language :: Python :: 3.6
Classifier: Programming Language :: Python :: 3.7
Classifier: Programming Language :: Python :: 3.8
Classifier: License :: OSI Approved :: MIT License
Classifier: Operating System :: POSIX :: Linux
Classifier: Operating System :: Microsoft :: Windows
Requires-Python: >=3.6
Requires-Dist: pyudev (>=0.21.0) ; sys_platform == "linux"
Requires-Dist: pywin32 (>=223) ; sys_platform == "win32"
Provides-Extra: nmap
Requires-Dist: python-nmap (>=0.6.1) ; extra == 'nmap'
